distributions_harsh/Binomialdistribution.py
distributions_harsh/Gaussiandistribution.py
distributions_harsh/Generaldistribution.py
distributions_harsh/__init__.py
distributions_harsh-0.1.dist-info/LICENSE
distributions_harsh-0.1.dist-info/METADATA
distributions_harsh-0.1.dist-info/WHEEL
distributions_harsh-0.1.dist-info/top_level.txt
distributions_harsh-0.1.dist-info/RECORD
