Metadata-Version: 2.1
Name: distributions-harsh
Version: 0.1
Summary: Gaussian and Binomial distributions
Home-page: UNKNOWN
Author: Harsh Bhandari
Author-email: harshbhandari32@gmail.com
License: UNKNOWN
Platform: UNKNOWN
Classifier: Programming Language :: Python :: 3
Classifier: License :: OSI Approved :: MIT License
Classifier: Operating System :: OS Independent
